{
  "1 Armstrong Road, Te Puna, Tauranga, 3174, NEW ZEALAND": [
    -37.693502273268,
    176.075788985973
  ],
  "1 Ballinabreen Road, Flat Bush, Auckland, 2019, NEW ZEALAND": [
    -36.980711690241,
    174.929786760752
  ],
  "1 Calder Crescent, Pokeno, Pokeno, 2402, NEW ZEALAND": [
    -37.249543204554,
    175.010001582564
  ],
  "1 Falcon Road, Rolleston, Rolleston, 7615, NEW ZEALAND": [
    -43.602936669999,
    172.403723808193
  ],
  "1 Moville Drive, Flat Bush, Auckland, 2019, NEW ZEALAND": [
    -36.974687481753,
    174.919375439603
  ],
  "1 Paripari Street, Flat Bush, Auckland, 2019, NEW ZEALAND": [
    -36.978181268544,
    174.936233458545
  ],
  "1 Peel Street, Gisborne, NEW ZEALAND": [
    -38.66535800447,
    178.026869063278
  ],
  "1 Tanekaha Road, Flat Bush, Auckland, 2019, NEW ZEALAND": [
    -36.976165672287,
    174.923602014279
  ],
  "1/32 Huia Road, Otahuhu, Auckland, NEW ZEALAND": [
    -36.941651629155,
    174.837132675538
  ],
  "10 Bellenden Crescent, Pokeno, Pokeno, 2402, NEW ZEALAND": [
    -37.247125486493,
    175.013278319972
  ],
  "10 Blowers Place, Flat Bush, Auckland, 2019, NEW ZEALAND": [
    -36.96859249704,
    174.901835469018
  ],
  "10 Demeter Street, Flat Bush, Auckland, 2019, NEW ZEALAND": [
    -36.978445298494,
    174.934463871147
  ],
  "10 Progressive Way, East Tamaki, Auckland, 2019, NEW ZEALAND": [
    -36.961876916216,
    174.898733326652
  ],
  "10 Shandon Street, Flat Bush, Auckland, 2019, NEW ZEALAND": [
    -36.971077312236,
    174.916594324129
  ],
  "101 Greenwood Street, Hamilton, NEW ZEALAND": [
    -37.790051486448,
    175.259801172646
  ],
  "101 Thomas Road, Flat Bush, Auckland, 2019, NEW ZEALAND": [
    -36.984103250776,
    174.912151328713
  ],
  "103 Northmoor Boulevard, Rolleston, Rolleston, 7615, NEW ZEALAND": [
    -43.620882031331,
    172.398515461198
  ],
  "1034 State Highway 12, Maungaturoto, NEW ZEALAND": [
    -36.121555332151,
    174.328375493329
  ],
  "107 Harleston Road, Rd 7, Sefton, 7477, NEW ZEALAND": [
    -43.235086371766,
    172.697499120933
  ],
  "107 Kirkbride Road, Mangere, Auckland, NEW ZEALAND": [
    -36.972310105142,
    174.786785182464
  ],
  "108 Thomas Road, Flat Bush, Auckland, 2019, NEW ZEALAND": [
    -36.983581393484,
    174.91225979054
  ],
  "109 Argento Avenue, Flat Bush, Auckland, 2019, NEW ZEALAND": [
    -36.967782805193,
    174.933410517375
  ],
  "109 Mt Aspiring Rd, Lake Wanaka, Nz, NEW ZEALAND": [
    -44.701038782811,
    169.110042801644
  ],
  "109 Mt Aspiring Road, Lake Wanaka, NEW ZEALAND": [
    -44.701038782811,
    169.110042801644
  ],
  "109 New Windsor Rd, New Windsor, Auckland, 1063, NEW ZEALAND": [
    -36.903767528433,
    174.7091350121
  ],
  "11 Silvana Drive, Flat Bush, Auckland, 2019, NEW ZEALAND": [
    -36.965603845644,
    174.930291611203
  ],
  "11 Whakahoki Road, Flat Bush, Auckland, 2019, NEW ZEALAND": [
    -36.971127436017,
    174.934137060742
  ],
  "11 Whetstone Road, Flat Bush, Auckland, 2019, NEW ZEALAND": [
    -36.972441927983,
    174.899807048449
  ],
  "1101 Omahu Road, Hastings, NEW ZEALAND": [
    -39.617943809483,
    176.812044000954
  ],
  "111 Garvie Rd., Hunua, Rd3 Papakura, Auckland, NEW ZEALAND": [
    -37.072399434202,
    175.044000006767
  ],
  "112 Mcquoids Road, Flat Bush, Auckland, 2019, NEW ZEALAND": [
    -36.981885105829,
    174.930712131285
  ],
  "112 Takanini School Road, Takanini, Papakura, NEW ZEALAND": [
    -37.029209792162,
    174.919541233647
  ],
  "112 Waterloo Road, Christchurch, NEW ZEALAND": [
    -43.538006759965,
    172.535129586484
  ],
  "114 Captain Springs Road, Onehunga, Auckland, NEW ZEALAND": [
    -36.925001445657,
    174.800695150532
  ],
  "114 Maui Street, Te Rapa, Hamilton, NEW ZEALAND": [
    -37.731957648756,
    175.222808045905
  ],
  "115 Ringer Road, Rd 7, Hamilton, 3287, NEW ZEALAND": [
    -37.791734029442,
    175.430826095599
  ],
  "1161 State Highway 2, Wairoa Road, Napier, NEW ZEALAND": [
    -39.378184931995,
    176.891995499326
  ],
  "117 Chadwick Rd, Greeton, Tauranga, NEW ZEALAND": [
    -37.727821888944,
    176.135875275339
  ],
  "119 Hillpark Drive, Pokeno, Pokeno, 2402, NEW ZEALAND": [
    -37.233459780725,
    175.014012928097
  ],
  "12 Aklander Rise, Flat Bush, Auckland, 2019, NEW ZEALAND": [
    -36.986175969702,
    174.912952973932
  ],
  "12 Ako Road, Flat Bush, Auckland, 2019, NEW ZEALAND": [
    -36.97640870557,
    174.924806996679
  ],
  "12 Ballindrait Drive, Flat Bush, Auckland, 2019, NEW ZEALAND": [
    -36.976590215683,
    174.914936132224
  ],
  "12 Delorean Drive, Rolleston, Rolleston, 7615, NEW ZEALAND": [
    -43.604808097521,
    172.392586438168
  ],
  "12 Hautoa Lane, Flat Bush, Auckland, 2019, NEW ZEALAND": [
    -36.982791902024,
    174.937386221689
  ],
  "12 Kerrykeel Drive, Flat Bush, Auckland, 2019, NEW ZEALAND": [
    -36.969834946548,
    174.915669800209
  ],
  "12 Lisnoble Road, Flat Bush, Auckland, 2019, NEW ZEALAND": [
    -36.979745289767,
    174.929378402852
  ],
  "12 Peter Bourne Drive, Pokeno, Pokeno, 2402, NEW ZEALAND": [
    -37.248112329863,
    175.009402108849
  ],
  "12 SYMES ROAD, SOCKBURN, CHRISTCHURCH, NEW ZEALAND": [
    -43.543015659574,
    172.549453253182
  ],
  "120 Joseph Street, Flat Bush, Auckland, 2019, NEW ZEALAND": [
    -36.985963530366,
    174.907799444584
  ],
  "122 Argento Avenue, Flat Bush, Auckland, 2019, NEW ZEALAND": [
    -36.967854302827,
    174.935811681177
  ],
  "122 Captain Springs Road, Onehunga, Auckland, NEW ZEALAND": [
    -36.924474559223,
    174.800596746989
  ],
  "123 Ormiston Road, Flat Bush, Auckland, 2019, NEW ZEALAND": [
    -36.964209180774,
    174.902961912985
  ],
  "124 Harriet Johnston Drive, Pokeno, Pokeno, 2402, NEW ZEALAND": [
    -37.249013384454,
    175.002998167185
  ],
  "126 Studholm St, Morrinsville, NEW ZEALAND": [
    -37.652559819469,
    175.523385273071
  ],
  "129 Flat Bush School Road, Flat Bush, Auckland, 2019, NEW ZEALAND": [
    -36.974416117638,
    174.917974572125
  ],
  "13 Alexandra Street, Te Awamutu, NEW ZEALAND": [
    -38.010204647672,
    175.325435481651
  ],
  "13 Hermes Road, Flat Bush, Auckland, 2019, NEW ZEALAND": [
    -36.978329837778,
    174.932089445615
  ],
  "13 Kerrykeel Drive, Flat Bush, Auckland, 2019, NEW ZEALAND": [
    -36.97015760791,
    174.915824781598
  ],
  "13 Treloar Crescent, Hobsonville, Auckland, 0616, NEW ZEALAND": [
    -36.8023508586,
    174.670842874176
  ],
  "13 Umbria Lane, Flat Bush, Auckland, 2019, NEW ZEALAND": [
    -36.980791686559,
    174.951033049706
  ],
  "13-15 Dilworth Avenue, Remuera, Auckland, NEW ZEALAND": [
    -36.876865852101,
    174.782806492775
  ],
  "131 Argento Avenue, Flat Bush, Auckland, 2019, NEW ZEALAND": [
    -36.967422886271,
    174.936720950034
  ],
  "131 Peel Street, Gisborne, NEW ZEALAND": [
    -38.668061335882,
    178.023631888453
  ],
  "138 Gracechurch Drive, Howick, Auckland, NEW ZEALAND": [
    -36.949459797214,
    174.912428518251
  ],
  "14 Black Shed Road, Flat Bush, Auckland, 2019, NEW ZEALAND": [
    -36.982518735799,
    174.931350413212
  ],
  "14 Fernly Rise, Flat Bush, Auckland, 2019, NEW ZEALAND": [
    -36.985538316418,
    174.908633024855
  ],
  "14 Hawkley Close, Flat Bush, Auckland, 2019, NEW ZEALAND": [
    -36.975153306022,
    174.903078756716
  ],
  "14 Hawkley Close,, Flat Bush, Auckland, 2019, NEW ZEALAND": [
    -36.975153306022,
    174.903078756716
  ],
  "14 Hirimate Place, Flat Bush, Auckland, 2019, NEW ZEALAND": [
    -36.984456128899,
    174.908794963224
  ],
  "14 Listack Drive, Flat Bush, Auckland, 2019, NEW ZEALAND": [
    -36.97361606498,
    174.919762432072
  ],
  "14 Te Hurunui Drive, Pegasus, North Canterbury, 7612, NEW ZEALAND": [
    -43.303520462151,
    172.698000023467
  ],
  "14 Tir Conaill Avenue, Flat Bush, Auckland, 2019, NEW ZEALAND": [
    -36.981127423691,
    174.908384417607
  ],
  "14 Tui Street, Matamata, NEW ZEALAND": [
    -37.812104107725,
    175.774288575991
  ],
  "140 Argento Avenue, Flat Bush, Auckland, 2019, NEW ZEALAND": [
    -36.966078596639,
    174.936651464057
  ],
  "142 Bodhisattva Road, Rd 1, Waitoki, 0994, NEW ZEALAND": [
    -36.617697028731,
    174.605842220879
  ],
  "1424 Maraekakaho Road, Hastings, NEW ZEALAND": [
    -39.656845745471,
    176.786057044187
  ],
  "15 Carrygawley Road, Flat Bush, Auckland, 2019, NEW ZEALAND": [
    -36.980092342468,
    174.929875282072
  ],
  "15 Flannery Road, Pokeno, Pokeno, 2402, NEW ZEALAND": [
    -37.250259060995,
    175.013670257765
  ],
  "15 Greenstone Place, Clover Park, Auckland, 2019, NEW ZEALAND": [
    -36.985141852398,
    174.89321652562
  ],
  "15 Helenvale Crescent, Pokeno, Pokeno, 2402, NEW ZEALAND": [
    -37.232855422065,
    175.016148786534
  ],
  "15 Millpark Lane, Hamilton, 3287, NEW ZEALAND": [
    -37.788176707825,
    175.405006481058
  ],
  "15-17 Hewlett Street, Whangarei, NEW ZEALAND": [
    -35.739661448514,
    174.342819607976
  ],
  "155 Clarkr Road, Hobsonville, Auckland, 0616, NEW ZEALAND": [
    -36.795199209263,
    174.66123008852
  ],
  "155 Roydvale Avenue, Christchurch, NEW ZEALAND": [
    -43.491366833212,
    172.565038899223
  ],
  "16 Falcon Road, Rolleston, Christchurch, 7615, NEW ZEALAND": [
    -43.603955783697,
    172.402460571566
  ],
  "16 Golden Avenue, Flat Bush, Auckland, 2019, NEW ZEALAND": [
    -36.976479197376,
    174.923906109726
  ],
  "16 Piki Street, Flat Bush, Auckland, 2019, NEW ZEALAND": [
    -36.986069896718,
    174.912280410022
  ],
  "161 Cashel Street, Christchurch Central, Christchurch 8011, NEW ZEALAND": [
    -43.532858553125,
    172.638693113177
  ],
  "166 Upper Sefton Road, Ashley Rd7, Rangiora, 7477, NEW ZEALAND": [
    -43.26572671219,
    172.625262202986
  ],
  "166 Upper Sefton Road, Rangiora, 7477, NEW ZEALAND": [
    -43.26572671219,
    172.625262202986
  ],
  "168 Youngson Road, Rd 7, Whakamarama, 3179, NEW ZEALAND": [
    -37.676310067846,
    176.005949543792
  ],
  "17 Ballyliffin Drive, Flat Bush, Auckland, 2019, NEW ZEALAND": [
    -36.981420203569,
    174.914778803901
  ],
  "17 Black Shed Road, Flat Bush, Auckland, 2019, NEW ZEALAND": [
    -36.982309439677,
    174.930891923109
  ],
  "17 Downs Road, Rd 6, Rangiora, 7476, NEW ZEALAND": [
    -43.450725644843,
    172.360767570972
  ],
  "17 Lime Hill Rise, Flat Bush, Auckland, 2019, NEW ZEALAND": [
    -36.984989008394,
    174.912184521049
  ],
  "17 Rakaia Rise, Clover Park, Auckland, 2019, NEW ZEALAND": [
    -36.987368965981,
    174.897602105
  ],
  "17 Rashni Road, Flat Bush, Auckland, 2019, NEW ZEALAND": [
    -36.975202968798,
    174.929282346242
  ],
  "17 Tanekaha Road, Flat Bush, Auckland, 2019, NEW ZEALAND": [
    -36.977127286129,
    174.9233369785
  ],
  "17 Tinaku Road, Flat Bush, Auckland, 2019, NEW ZEALAND": [
    -36.969984437791,
    174.930757142106
  ],
  "170 Broadway Avenue, Palmerston North, NEW ZEALAND": [
    -40.352825089522,
    175.616029023945
  ],
  "176 Whitmore Road, Rd 2, Palmerston North, 4472, NEW ZEALAND": [
    -40.419264035495,
    175.576646065142
  ],
  "179 Te Irirangi Drive, Flat Bush, Auckland, 2019, NEW ZEALAND": [
    -36.975294331543,
    174.898816475132
  ],
  "18 Brookview Drive, Flat Bush, Flat Bush, Auckland, 2019, NEW ZEALAND": [
    -36.97273734816,
    174.91298172386
  ],
  "18 Darnell Crescent, Clover Park, Auckland, 2019, NEW ZEALAND": [
    -36.98351676901,
    174.900496879081
  ],
  "18 Drumbuoy Drive, Flat Bush, Auckland, 2019, NEW ZEALAND": [
    -36.977723574721,
    174.918483772743
  ],
  "18 Goodfellow Lane, Flat Bush, Auckland, 2019, NEW ZEALAND": [
    -36.984734952908,
    174.926534087829
  ],
  "18 Maniapoto Street, Otorohanga, NEW ZEALAND": [
    -38.185397404332,
    175.211642596504
  ],
  "183 Terapa Road, Hamilton, 2001, NEW ZEALAND": [
    -37.767966011431,
    175.260999936266
  ],
  "187b Morrinsville Rd, Hamilton, NEW ZEALAND": [
    -37.797188697426,
    175.331459567899
  ],
  "19 Aklander Rise, Flat Bush, Auckland, 2019, NEW ZEALAND": [
    -36.986499343527,
    174.912593222648
  ],
  "19 Castlederg Drive, Flatbush, Auckland, 2019, NEW ZEALAND": [
    -36.974983698211,
    174.918777893725
  ],
  "19 Ormiston Road, East Tamaki, Auckland, 2019, NEW ZEALAND": [
    -36.962134701648,
    174.891721361732
  ],
  "19 Ridgehill Rise, Flat Bush, Auckland, 2019, NEW ZEALAND": [
    -36.984746226568,
    174.939789397148
  ],
  "19 Station Street, Hobsonville, Auckland, 0616, NEW ZEALAND": [
    -36.791033990118,
    174.656493391216
  ],
  "19 Timmer Road, Flat Bush, Auckland, 2019, NEW ZEALAND": [
    -36.970747274799,
    174.925518368802
  ],
  "193 Redoubt Road, Flat Bush, Auckland, 2019, NEW ZEALAND": [
    -36.988841498731,
    174.910082758828
  ],
  "1st Floor, 217 Great South Road, Greenlane, Auckland, NEW ZEALAND": [
    -36.891275349488,
    174.79488665927
  ],
  "2 Gecko Road, Hobsonville, Auckland, 0616, NEW ZEALAND": [
    -36.795825882254,
    174.662224098417
  ],
  "2 Pacific Cove Drive, Papamoa, NEW ZEALAND": [
    -37.70589169008,
    176.284419501333
  ],
  "20 Arawa Street, Matamata, NEW ZEALAND": [
    -37.811717287602,
    175.772202882674
  ],
  "20 Farmdale Court, Flat Bush, Auckland, 2019, NEW ZEALAND": [
    -36.971913071802,
    174.901499438519
  ],
  "20 Grand Ridge Avenue, Flat Bush, Auckland, 2019, NEW ZEALAND": [
    -36.983962225255,
    174.941607264309
  ],
  "20 Tims Crescent, Flat Bush, Auckland, 2019, NEW ZEALAND": [
    -36.968282953356,
    174.936784820136
  ],
  "204 Busby Road, Rd 3, Tahawai, 3170, NEW ZEALAND": [
    -37.556221912408,
    175.888362338714
  ],
  "21 Alison Rd, Surfdale, Waiheke Island, Auckland, NEW ZEALAND": [
    -36.794553802719,
    175.029125900487
  ],
  "21 Hensley Crescent, Flagstaff, Hamilton, Hamilton, NEW ZEALAND": [
    -37.730929356874,
    175.238697535935
  ],
  "22 Jellicoe Street, Freemans Bay, Auckland 1010, NEW ZEALAND": [
    -36.84137565868,
    174.757469256761
  ],
  "22 Ormiston Road, Otara, Auckland, 2019, NEW ZEALAND": [
    -36.960320145339,
    174.893018377429
  ],
  "23 Casheltown Way, Flat Bush, Auckland, 2019, NEW ZEALAND": [
    -36.979005922088,
    174.918105078357
  ],
  "23 Dissmeyer Drive, Clover Park, Auckland, 2019, NEW ZEALAND": [
    -36.980412237803,
    174.897638817736
  ],
  "23 Frisken Road, Flat Bush, Auckland, 2019, NEW ZEALAND": [
    -36.973587524599,
    174.924232836312
  ],
  "23 Hikuawa Roadroad, Flat Bush, Auckland, 2019, NEW ZEALAND": [
    -36.975049328513,
    174.912388871849
  ],
  "23 La Bella Road, Hobsonville, Auckland, 0616, NEW ZEALAND": [
    -36.796172557769,
    174.664391323302
  ],
  "23 Texel Crescent, West Melton, West Melton, 7618, NEW ZEALAND": [
    -43.52800685611,
    172.383368440151
  ],
  "236 Redoubt Road, Totara Park, Auckland, 2019, NEW ZEALAND": [
    -36.99025875283,
    174.916608908641
  ],
  "24 Christella Street, Flat Bush, Auckland, 2019, NEW ZEALAND": [
    -36.985399302554,
    174.92626561547
  ],
  "24 Drumbuoy Drive, Flat Bush, Auckland, 2019, NEW ZEALAND": [
    -36.978133198329,
    174.918304483834
  ],
  "24 Riviera Drive, Flat Bush, Auckland, 2019, NEW ZEALAND": [
    -36.972260040684,
    174.914908136667
  ],
  "24 Rosewell Crescent, Flat Bush, Auckland, 2019, NEW ZEALAND": [
    -36.968528878395,
    174.915575168522
  ],
  "24 Terrasini Drive, Flat Bush, Auckland, 2019, NEW ZEALAND": [
    -36.964622534329,
    174.934595383208
  ],
  "25 Donnolly Street, St. Johns, Auckland, NEW ZEALAND": [
    -36.88151034847,
    174.839208654519
  ],
  "25 Hangahai Road, Flat Bush, Auckland, 2019, NEW ZEALAND": [
    -36.970729798531,
    174.930908854553
  ],
  "25 Pukanui Avenue, Totara Park, Auckland, 2019, NEW ZEALAND": [
    -36.991456610612,
    174.926503996796
  ],
  "25 Willoughby Street, Paeroa, NEW ZEALAND": [
    -37.38100107084,
    175.672848788447
  ],
  "26 Bendridge Street, Flat Bush, Auckland, 2019, NEW ZEALAND": [
    -36.98312374157,
    174.935819392528
  ],
  "26 Kilcooley Road, Flat Bush, Auckland, 2019, NEW ZEALAND": [
    -36.967173734199,
    174.936924462643
  ],
  "267 Grey Street, Gisborne, NEW ZEALAND": [
    -38.66867962697,
    178.018939363779
  ],
  "27 Loch Views Road, Rd 5, Taupo, 3385, NEW ZEALAND": [
    -38.701702146186,
    176.007665319372
  ],
  "27 Pilot Drive, Hobsonville, Auckland, 0616, NEW ZEALAND": [
    -36.804081805425,
    174.658256021635
  ],
  "272 Redoubt Road, Totara Park, Auckland, 2019, NEW ZEALAND": [
    -36.993290696756,
    174.917861248794
  ],
  "28 Carrygawley Road, Flat Bush, Auckland, 2019, NEW ZEALAND": [
    -36.981109193052,
    174.92993864926
  ],
  "28 Hartford Crescent, Rolleston, Rolleston, 7615, NEW ZEALAND": [
    -43.621682544994,
    172.383782673806
  ],
  "29 Hikuawa Road, Flat Bush, Auckland, 2019, NEW ZEALAND": [
    -36.975573574647,
    174.912237578496
  ],
  "29 Raphoe Road, Flat Bush, Auckland, 2019, NEW ZEALAND": [
    -36.97995881875,
    174.903252848845
  ],
  "2a Liscooly Place, Flat Bush, Auckland, 2019, NEW ZEALAND": [
    -36.980442664111,
    174.903511011462
  ],
  "2nd Floor, 18 Woollcombe Street, Timaru 7910, 0000, NEW ZEALAND": [
    -44.399065046757,
    171.254763701584
  ],
  "3 Aitkenhead Street, Pokeno, Waikato, 2402, NEW ZEALAND": [
    -37.253532152275,
    175.005985896572
  ],
  "3 Beltany Drive, Flat Bush, Auckland, 2019, NEW ZEALAND": [
    -36.977692896956,
    174.915296302603
  ],
  "3 Boundary Road, Hobsonville, Auckland, 0616, NEW ZEALAND": [
    -36.788900502393,
    174.671173288799
  ],
  "3 Devine Drive, Rd 8, Rolleston, 7678, NEW ZEALAND": [
    -43.563653581573,
    172.461461626208
  ],
  "3 Joseph Street, Flat Bush, Auckland, 2019, NEW ZEALAND": [
    -36.983416940544,
    174.910071610897
  ],
  "3 Skanda Crescent, Flat Bush, Auckland, 2019, NEW ZEALAND": [
    -36.973072205192,
    174.929459539675
  ],
  "3 Taita Drive, Rolleston, Rolleston, 7615, NEW ZEALAND": [
    -43.606057126823,
    172.398558628
  ],
  "3 Taita Drive, Rolleston, Rolleston, 7678, NEW ZEALAND": [
    -43.606057126823,
    172.398558628
  ],
  "3 Tia Road, Flat Bush, Auckland, 2019, NEW ZEALAND": [
    -36.967855350565,
    174.914125686006
  ],
  "30 Ballyalton Crescent, Flat Bush, Auckland, 2109, NEW ZEALAND": [
    -36.985065786627,
    174.917176531124
  ],
  "30 Buckland Road, Mangere, Auckland, NEW ZEALAND": [
    -36.973252835205,
    174.834647893363
  ],
  "30 Cooladawson Drive, Flat Bush, Auckland, 2019, NEW ZEALAND": [
    -36.981498658183,
    174.908568568019
  ],
  "30 Diorella Drive, Clover Park, Auckland, 2019, NEW ZEALAND": [
    -36.989065924189,
    174.890182611947
  ],
  "30 Ngaki Street, Flat Bush, Auckland, 2019, NEW ZEALAND": [
    -36.971235227292,
    174.931344713518
  ],
  "30a Laurel Drive, Rd 7, Whakamarama, 3179, NEW ZEALAND": [
    -37.707399887828,
    175.990445202212
  ],
  "31 Hurley Drive, Rolleston, Rolleston, 7615, NEW ZEALAND": [
    -43.623936061572,
    172.398669101484
  ],
  "32 Drumnaconagher Road, Flat Bush, Auckland, 2019, NEW ZEALAND": [
    -36.983903803389,
    174.916173301132
  ],
  "32 Kilcooley Road, Flat Bush, Auckland, 2019, NEW ZEALAND": [
    -36.967214679796,
    174.937382030737
  ],
  "32 Skua Road, Hobsonville, Auckland, 0616, NEW ZEALAND": [
    -36.79739053212,
    174.661565783742
  ],
  "32 Tamure Road, Flat Bush, Auckland, 2019, NEW ZEALAND": [
    -36.971675947761,
    174.933622747163
  ],
  "33 Carrygawley Road, Flat Bush, Auckland, 2019, NEW ZEALAND": [
    -36.981637965414,
    174.929451995962
  ],
  "33 Yorke Road, Haruru, Haruru, 0204, NEW ZEALAND": [
    -35.278658410959,
    174.059047818754
  ],
  "338 Victoria Road, Rydalmere, 2116, AUSTRALIA": [
    -33.809911177405,
    151.038093525468
  ],
  "339 Lavenham Road, Patutahi, Gisborne, NEW ZEALAND": [
    -38.596659632678,
    177.899919020897
  ],
  "34 Carrygawley Road, Flat Bush, Auckland, 2019, NEW ZEALAND": [
    -36.981487426433,
    174.929818620407
  ],
  "34 GRAYSON AVE, PAPATOETOE, NEW ZEALAND": [
    -36.988174190326,
    174.865613196897
  ],
  "34 Hitchen Road, Pokeno, Waikato, 2402, NEW ZEALAND": [
    -37.247886772849,
    175.012977325829
  ],
  "34,deodar Place,totara Heights,auckland., Auckland, 2015, NEW ZEALAND": [
    -37.002493858804,
    174.900279871607
  ],
  "341b Redoubt Road, Totara Park, Auckland, 2019, NEW ZEALAND": [
    -36.997721035498,
    174.923074792569
  ],
  "35 Hobson St, Auckland, NEW ZEALAND": [
    -36.846792798884,
    174.761965812539
  ],
  "35 Randolph Street,, Newton., NEW ZEALAND": [
    -36.862342947564,
    174.757129370587
  ],
  "36 Dromoland Drive, Flat Bush, Auckland, 2019, NEW ZEALAND": [
    -36.970836961163,
    174.917422120887
  ],
  "36 Kilcooley Road, Flat Bush, Auckland, 2019, NEW ZEALAND": [
    -36.967258936245,
    174.937698699039
  ],
  "36, Dromoland Drive, Flatbush, Auckland, 2019, NEW ZEALAND": [
    -36.970836961163,
    174.917422120887
  ],
  "37 Finn Avenue, Rolleston, Rolleston, 7615, NEW ZEALAND": [
    -43.620318935076,
    172.406500397439
  ],
  "37 Peninsula Road, Mangere, NEW ZEALAND": [
    -36.980358845079,
    174.800481328182
  ],
  "37 Rosewell Crescent, Flat Bush, Auckland, 2019, NEW ZEALAND": [
    -36.967591949258,
    174.915533594282
  ],
  "37 Tiritiri Moana Drive, Pegasus, Pegasus, 7612, NEW ZEALAND": [
    -43.304221273076,
    172.697046330523
  ],
  "38 Charlestown Drive, Flat Bush, Auckland, 2019, NEW ZEALAND": [
    -36.977301881172,
    174.913475669414
  ],
  "39 Chandler Way, Rolleston, Rolleston, 7615, NEW ZEALAND": [
    -43.61688440834,
    172.391337534595
  ],
  "39 Kitenga Road, Flat Bush, Auckland, 2019, NEW ZEALAND": [
    -36.969873000388,
    174.945796958611
  ],
  "39 Ksenia Drive, Flat Bush, Auckland, 2019, NEW ZEALAND": [
    -36.976838822931,
    174.907979739321
  ],
  "39 Silvana Drive, Flat Bush, Auckland, 2019, NEW ZEALAND": [
    -36.964463781083,
    174.927898158751
  ],
  "39 Tims Crescent, Flat Bush, Auckland, 2019, NEW ZEALAND": [
    -36.967865618396,
    174.9373783427
  ],
  "39 Vestey Drive, Mt Wellington, NEW ZEALAND": [
    -36.923703130765,
    174.83969589455
  ],
  "399 Ormiston Road, Flat Bush, Auckland, 2019, NEW ZEALAND": [
    -36.968278594766,
    174.930054151886
  ],
  "4 Elevation Street, Flat Bush, Auckland, 2019, NEW ZEALAND": [
    -36.986097724636,
    174.910464303061
  ],
  "4 Glenkirk Crescent, Pokeno, Pokeno, 2402, NEW ZEALAND": [
    -37.233889665098,
    175.012295625644
  ],
  "4 Hauhake Road, Flat Bush, Auckland, 2019, NEW ZEALAND": [
    -36.9817612213,
    174.93241189743
  ],
  "4 Paul Way, Pokeno, Waikato, 2402, NEW ZEALAND": [
    -37.252729417408,
    175.005327414258
  ],
  "4 Rothwell Avenue, Albany Industrial Estate, Albany, Auckland, NEW ZEALAND": [
    -36.75277424825,
    174.698684203764
  ],
  "4 Urney Drive, Flat Bush, Auckland, 2019, NEW ZEALAND": [
    -36.974491303309,
    174.91470269622
  ],
  "4 Walter Little Way, Flat Bush, Auckland, 2019, NEW ZEALAND": [
    -36.97083893091,
    174.903778561812
  ],
  "4 Willowherb Lane, Hobsonville, Auckland, 0616, NEW ZEALAND": [
    -36.800563501567,
    174.658760863663
  ],
  "4/35 Sir William Pickering Drive, Canterbury Technology Park, Christchurch, NEW ZEALAND": [
    -43.497954967198,
    172.559313640259
  ],
  "40 Raphoe Road, Flat Bush, Auckland, 2019, NEW ZEALAND": [
    -36.979792312244,
    174.904303268951
  ],
  "41/19 Ormiston Road, Otara, Auckland, 2019, NEW ZEALAND": [
    -36.962134701648,
    174.891721361732
  ],
  "42 Shepherds Lane, Flat Bush, Auckland, 2019, NEW ZEALAND": [
    -36.971910724869,
    174.936510480445
  ],
  "43 Broadhurst Road, Flat Bush, Auckland, 2019, NEW ZEALAND": [
    -36.975329619355,
    174.907487218691
  ],
  "43 Gabriel's Gully Road, Rd3, Lawrence, 9093, NEW ZEALAND": [
    -45.908999991406,
    169.684286026119
  ],
  "44 Drumconnell Drive, Flat Bush, Auckland, 2019, NEW ZEALAND": [
    -36.979018620671,
    174.909269043668
  ],
  "44 Drumnaconagher Road, Flat Bush, Auckland, 2019, NEW ZEALAND": [
    -36.983453150365,
    174.91537970254
  ],
  "44 Hughs Way, Flat Bush, Auckland, 2019, NEW ZEALAND": [
    -36.976077410847,
    174.915751859041
  ],
  "44 Lucca Crescent, Rolleston, 7615, NEW ZEALAND": [
    -43.602139257641,
    172.398027550614
  ],
  "44-50 Gateway Park Drive, Pokeno, Pokeno, 2042, NEW ZEALAND": [
    -37.247364119276,
    175.016152139295
  ],
  "45 Donegal Park Drive, Flat Bush, Auckland, 2019, NEW ZEALAND": [
    -36.976225309529,
    174.908030617474
  ],
  "45 Hangahai Road, Flat Bush, Auckland, 2019, NEW ZEALAND": [
    -36.97120161586,
    174.932926211009
  ],
  "45-49 Tirau Street, Putaruru, NEW ZEALAND": [
    -38.048933315114,
    175.78069645715
  ],
  "46 Brooke Ridge Rise, Parklands Estate, Auckland, NEW ZEALAND": [
    -36.943091688186,
    174.921409727503
  ],
  "47 Valderama Drive, Flat Bush, Auckland, 2019, NEW ZEALAND": [
    -36.965656358267,
    174.931166514257
  ],
  "475 Ormiston Road, Flat Bush, Auckland, 2019, NEW ZEALAND": [
    -36.969606112705,
    174.936794968178
  ],
  "48 Rathfarnham Road, Flat Bush, Auckland, 2019, NEW ZEALAND": [
    -36.983017752405,
    174.93667107771
  ],
  "480 Selwyn Street, Christchurch, NEW ZEALAND": [
    -43.539137227246,
    172.622026117808
  ],
  "5 Cyperus Street, Flat Bush, Auckland, 2019, NEW ZEALAND": [
    -36.985488988918,
    174.927350988112
  ],
  "5 Finbar Close, Flat Bush, Auckland, 2019, NEW ZEALAND": [
    -36.963849303761,
    174.924638688064
  ],
  "5 Hansworth Place, Flat Bush, Auckland, 2019, NEW ZEALAND": [
    -36.973086035332,
    174.902094888921
  ],
  "5 Harakeke Terrace, Whitford, Whitford, 2019, NEW ZEALAND": [
    -36.975095638528,
    174.949873497221
  ],
  "5 Mccathie Drive, Flat Bush, Auckland, 2019, NEW ZEALAND": [
    -36.962408119329,
    174.919253818188
  ],
  "5 Pah Road, Howick Auckland, NEW ZEALAND": [
    -36.900814164849,
    174.948613445716
  ],
  "5 Progressive Way, Flat Bush, Auckland, 2019, NEW ZEALAND": [
    -36.961893106561,
    174.897377789388
  ],
  "5/586, Papatoetoe, Manukau,, 2021, NEW ZEALAND": [
    -36.9682,
    174.84019
  ],
  "5/8 Laidlaw Way, East Tamaki, Auckland, 2019, NEW ZEALAND": [
    -36.96138917327,
    174.895797816522
  ],
  "50 Hikuawa Road, Flat Bush, Auckland, 2019, NEW ZEALAND": [
    -36.977212823451,
    174.91224855879
  ],
  "50 Patiki Road, Avondale Auckland, NEW ZEALAND": [
    -36.870316913758,
    174.666349768889
  ],
  "50 Sovereign Street, Flat Bush, Auckland, 2019, NEW ZEALAND": [
    -36.974374752945,
    174.938945674775
  ],
  "51 Bushfield Drive, Flat Bush, Auckland, 2019, NEW ZEALAND": [
    -36.982269499908,
    174.918233656752
  ],
  "51 Hughs Way, Flat Bush, Auckland, 2019, NEW ZEALAND": [
    -36.975621225767,
    174.914766650142
  ],
  "51-53 Maurice Road, Penrose, Auckland, NEW ZEALAND": [
    -36.919082774277,
    174.80980057959
  ],
  "51-A, Boundary Rd., Mt.Roskill, Auckland, NEW ZEALAND": [
    -36.914638018661,
    174.715703155247
  ],
  "513 King Street North, Hastings, NEW ZEALAND": [
    -39.635901800187,
    176.848360233404
  ],
  "52 Thomas Road, Flat Bush, Auckland, 2019, NEW ZEALAND": [
    -36.982577492941,
    174.907183039425
  ],
  "520 Great South Road, Greenlane, Auckland, NEW ZEALAND": [
    -36.893429624333,
    174.798388031683
  ],
  "55 Farnborough Way, Rolleston, Rolleston, 7615, NEW ZEALAND": [
    -43.614551263682,
    172.391979253102
  ],
  "56 Lime Hill Rise, Flat Bush, Auckland, 2019, NEW ZEALAND": [
    -36.984161672641,
    174.911602816969
  ],
  "560 Great South Road, Otahuhu, NEW ZEALAND": [
    -36.949911539885,
    174.845356948136
  ],
  "562 Richmond Road, Grey Lynn, Auckland, 1020, NEW ZEALAND": [
    -36.86152520909,
    174.733162575743
  ],
  "568 Springston Rolleston Road, Rolleston, Rolleston, 7615, NEW ZEALAND": [
    -43.608660168764,
    172.39402678441
  ],
  "578 Roto-O-Rangi Road, Rd 3, Cambridge, NEW ZEALAND": [
    -37.961554698628,
    175.463673181582
  ],
  "58 Cooladawson Drive, Flat Bush, Auckland, 2019, NEW ZEALAND": [
    -36.980398784848,
    174.910132379695
  ],
  "58 Medvale Avenue, Flat Bush, Auckland, 2019, NEW ZEALAND": [
    -36.974703155912,
    174.9006475857
  ],
  "583 Rosebank Road, Avondale, Auckland, NEW ZEALAND": [
    -36.877462308331,
    174.670311629153
  ],
  "59 Koromeke Street, Flat Bush, Auckland, 2019, NEW ZEALAND": [
    -36.98495124792,
    174.91801220687
  ],
  "6 Baratheon Road, Rolleston, Rolleston, 7615, NEW ZEALAND": [
    -43.613692495792,
    172.409195933682
  ],
  "6 Blake Street, Rangiora, NEW ZEALAND": [
    -43.302285975452,
    172.593351627045
  ],
  "6 Dunaff Place, Flat Bush, Auckland, 2019, NEW ZEALAND": [
    -36.979394381391,
    174.908244523643
  ],
  "6 Eastfield Avenue, Flat Bush, Auckland, 2019, NEW ZEALAND": [
    -36.975856799155,
    174.908519785343
  ],
  "6 La Bella Road, Hobsonville, Auckland, 0616, NEW ZEALAND": [
    -36.79570853561,
    174.6643516769
  ],
  "6 Longcot Drive, Rolleston, Rolleston, 7615, NEW ZEALAND": [
    -43.621895738701,
    172.388479221793
  ],
  "6 Mullafin Rd, Flat Bush, Auckland, 2019, NEW ZEALAND": [
    -36.977239310265,
    174.917635440322
  ],
  "6 Scott Road, Hobsonville, Auckland, 0616, NEW ZEALAND": [
    -36.80196474623,
    174.65715271172
  ],
  "6 Seawind Way, Hobsonville, Auckland, 0616, NEW ZEALAND": [
    -36.806991918388,
    174.665606112529
  ],
  "60 Cooladawson Drive, Flat Bush, Auckland, 2019, NEW ZEALAND": [
    -36.980403059619,
    174.910289540379
  ],
  "61 Chapel Road, Manukau, Auckland, NEW ZEALAND": [
    -36.975031307421,
    174.903935890134
  ],
  "61 Hikuawa Road, Flat Bush, Auckland, 2019, NEW ZEALAND": [
    -36.978528405064,
    174.910435720771
  ],
  "63 Hooper Road, Rd 6, Hamilton, 3286, NEW ZEALAND": [
    -37.753139179085,
    175.423550100729
  ],
  "63 Multose Drive, Flat Bush, Auckland, 2019, NEW ZEALAND": [
    -36.96264524337,
    174.918825670573
  ],
  "63 Rosewell Crescent, Flat Bush, Auckland, 2019, NEW ZEALAND": [
    -36.969428382334,
    174.915375595407
  ],
  "66 High Street, Leeston, NEW ZEALAND": [
    -43.762158380711,
    172.299061665451
  ],
  "66 Middlefield Drive, Dannemora, NEW ZEALAND": [
    -36.949829061958,
    174.913638445974
  ],
  "67 Charlestown Drive, Flat Bush, Auckland, 2019, NEW ZEALAND": [
    -36.979713354716,
    174.91226146692
  ],
  "69 Mandival Avenue, Flat Bush, Auckland, 2019, NEW ZEALAND": [
    -36.962125230097,
    174.928210971378
  ],
  "692 East Coast Road, Pinehill, Auckland, 0623, NEW ZEALAND": [
    -36.727398794437,
    174.727505071969
  ],
  "7 Annmarie Avenue, Totara Park, Auckland, 2019, NEW ZEALAND": [
    -36.992318479806,
    174.936941477906
  ],
  "7 Cloonlyon Drive, Flat Bush, Auckland, 2019, NEW ZEALAND": [
    -36.980764738741,
    174.914037340746
  ],
  "7 Gospel Heights, Flat Bush, Auckland, 2019, NEW ZEALAND": [
    -36.985549841535,
    174.90721715377
  ],
  "7 Greenan Drive, Flat Bush, Auckland, 2019, NEW ZEALAND": [
    -36.982094695318,
    174.909663328393
  ],
  "70 Maui Street, Hamilton, NEW ZEALAND": [
    -37.735375160228,
    175.224474535894
  ],
  "70 Michael Bosher Way, Flat Bush, Auckland, 2019, NEW ZEALAND": [
    -36.983116072129,
    174.939350436879
  ],
  "701 Selwyn Road, Rd 8, Rolleston, 7678, NEW ZEALAND": [
    -43.624683559697,
    172.402963737213
  ],
  "701 Selwyn Road, Rolleston, 7678, NEW ZEALAND": [
    -43.624683559697,
    172.402963737213
  ],
  "72 Finn Avenue, Rolleston, Rolleston, 7615, NEW ZEALAND": [
    -43.620426223437,
    172.407163154523
  ],
  "72 Ksenia Drive, Flat Bush, Auckland, 2019, NEW ZEALAND": [
    -36.976551994205,
    174.908273022114
  ],
  "72 Shaw Road, Pleasant Valley, Geraldine, NEW ZEALAND": [
    -44.093483530028,
    171.199888052046
  ],
  "73-75 Bridgman Street, Dunedin, NEW ZEALAND": [
    -45.891181764806,
    170.497573519578
  ],
  "74 Broadway Parade, Rolleston, Rolleston, 7615, NEW ZEALAND": [
    -43.617256103837,
    172.405637983422
  ],
  "74 Koromeke Street, Flat Bush, Auckland, 2019, NEW ZEALAND": [
    -36.985768232022,
    174.91880605692
  ],
  "74 Michael Bosher Way, Flat Bush, Auckland, 2019, NEW ZEALAND": [
    -36.982949858989,
    174.939113815752
  ],
  "8 Astoria Street, Rolleston, Rolleston, 7615, NEW ZEALAND": [
    -43.615358901962,
    172.410916403127
  ],
  "8 Beltany Drive, Flat Bush, Auckland, 2019, NEW ZEALAND": [
    -36.978043511965,
    174.914870921017
  ],
  "8 Carrick Glen Avenue, Flat Bush, Auckland, 2019, NEW ZEALAND": [
    -36.977727598035,
    174.904427656394
  ],
  "8 Coast Garden Drive, Hobsonville, Auckland, 0616, NEW ZEALAND": [
    -36.804024431298,
    174.659961906569
  ],
  "8 Galora Close, Flat Bush, Auckland, 2019, NEW ZEALAND": [
    -36.965762934166,
    174.920273644347
  ],
  "8 Lisnoble Road, Flat Bush, Auckland, 2019, NEW ZEALAND": [
    -36.979502968946,
    174.92944872702
  ],
  "81 Rookwood Avenue, Christchurch, NEW ZEALAND": [
    -43.495355068471,
    172.711096160445
  ],
  "85 Gala Street, Invercargill, NEW ZEALAND": [
    -46.406553572233,
    168.352208113462
  ],
  "85 Harriet Johnston Drive, Pokeno, Pokeno, 2402, NEW ZEALAND": [
    -37.247692564152,
    175.006399627312
  ],
  "86 Drumbuoy Drive, Flat Bush, Auckland, 2019, NEW ZEALAND": [
    -36.983285763759,
    174.913163443521
  ],
  "87 Anzac Avenue, Auckland City Central, NEW ZEALAND": [
    -36.848108506225,
    174.772860107372
  ],
  "88 Shortland Street, Auckland, NEW ZEALAND": [
    -36.846265325717,
    174.769754360788
  ],
  "9 Alta Terrace, Flat Bush, Auckland, 2019, NEW ZEALAND": [
    -36.983847435091,
    174.902499986301
  ],
  "9 Bunbeg Crescent, Flat Bush, Auckland, 2019, NEW ZEALAND": [
    -36.979742062734,
    174.913860063494
  ],
  "9 Francis Place, Wellington, NEW ZEALAND": [
    -41.297845529065,
    174.779479463948
  ],
  "9 Toscana Drive, Flat Bush, Auckland, 2019, NEW ZEALAND": [
    -36.976517418854,
    174.93983256395
  ],
  "9 Turret Lane, Hobsonville, Auckland, 0616, NEW ZEALAND": [
    -36.804890575262,
    174.667825389033
  ],
  "9 Yorke Road, Haruru, Haruru, 0204, NEW ZEALAND": [
    -35.280437676832,
    174.058382908841
  ],
  "918b Great South Road, Penrose, Auckland, NEW ZEALAND": [
    -36.916575160304,
    174.825298467104
  ],
  "94 Tir Conaill Avenue, Flat Bush, Auckland, 2019, NEW ZEALAND": [
    -36.984000153366,
    174.915745572613
  ],
  "96 Joseph Street, Flat Bush, Auckland, 2019, NEW ZEALAND": [
    -36.986746819218,
    174.908127763731
  ],
  "Building P, 61-69 Patiki Road, Avondale, Auckland 1026, NEW ZEALAND": [
    -36.86866281874,
    174.666606241216
  ],
  "Chartered Acccountants, 45-49 Tirau Street, Putaruru, NEW ZEALAND": [
    -38.048933315114,
    175.78069645715
  ],
  "Chertsey Road, Methven, NEW ZEALAND": [
    -43.635079068158,
    171.652667951839
  ],
  "Cnr Bristol And Exeter Streets, Levin, NEW ZEALAND": [
    -40.619416381521,
    175.286918205808
  ],
  "Cnr Wairau  Road & Diana Drive, Glenfield, Auckland, NEW ZEALAND": [
    -36.771196917059,
    174.738408473664
  ],
  "Cu-1-3 Shed 24, Princes Wharf, Auckland 1010, NEW ZEALAND": [
    -36.850007426389,
    174.769423610889
  ],
  "D/5-7 Collard Place Henderson, Auckland, NEW ZEALAND": [
    -36.853217443849,
    174.634103651454
  ],
  "Flat 2, 10 Hilltop Road, Clover Park, Auckland, 2019, NEW ZEALAND": [
    -36.984958582085,
    174.903674123298
  ],
  "Flat 2, 20 Darnell Crescent, Clover Park, Auckland, 2019, NEW ZEALAND": [
    -36.983646269414,
    174.900575501332
  ],
  "Ground Floor, 162 Grafton Road, Grafton, Auckland, NEW ZEALAND": [
    -36.864234365925,
    174.764438390156
  ],
  "Level 1 21 El Kobar Drive, Highbrook, Auckland, 2161, NEW ZEALAND": [
    -36.941466688617,
    174.872305856493
  ],
  "Level 1, 139 Vincent Street, City Central, Auckland, NEW ZEALAND": [
    -36.854414882536,
    174.759015801716
  ],
  "Level 1, 320 Ti Rakau Drive, East Tamaki, Auckland, 2163, NEW ZEALAND": [
    -36.927140046343,
    174.899623736227
  ],
  "Level 1, 46 Stanley Street, Parnell, Auckland, 0000, NEW ZEALAND": [
    -36.855351201389,
    174.771532652845
  ],
  "Level 1, 65 Centennial Avenue, Alexandra, 9020, NEW ZEALAND": [
    -45.251287508407,
    169.38841536147
  ],
  "Level 3, 130 Quay Street, Auckland, NEW ZEALAND": [
    -36.844008917382,
    174.769210710548
  ],
  "Level 3, 15b Vestey Drive, Mt Wellington, Auckland, NEW ZEALAND": [
    -36.927755948588,
    174.837050733546
  ],
  "Level 3, Cnr Walding & Rangitikei Streets, Palmerston North, NEW ZEALAND": [
    -40.352987907991,
    175.6086452378
  ],
  "Level 6 General Buildings, 33 Shortland Street, Auckland, NEW ZEALAND": [
    -36.846927244611,
    174.767448163949
  ],
  "Level 6, 130 Broadway, Newmarket, Auckland, NEW ZEALAND": [
    -36.867542325923,
    174.778475479585
  ],
  "Level 6, 5 Short Street, Newmarket, Auckland, 1049, NEW ZEALAND": [
    -36.866569228874,
    174.777080814716
  ],
  "Level 6, Ipayroll House, 93 Boulcott Street, Wellington, 6010, NEW ZEALAND": [
    -41.2862584,
    174.7741114
  ],
  "Level 6,berl House, 108 The Terrace, Wellington, 6042, NEW ZEALAND": [
    -41.282864464364,
    174.774684677202
  ],
  "Level One, 162 Dee Street, Invercargill, NEW ZEALAND": [
    -46.408245627027,
    168.34691980311
  ],
  "Lot 5, 1744 Dairy Flat Highway, Silverdale, 0994, NEW ZEALAND": [
    -36.62952401984,
    174.661924026283
  ],
  "Mcartney Street, Blenheim, NEW ZEALAND": [
    -41.516235425414,
    173.963090475497
  ],
  "Meadows Road, Washdyke, Timaru, NEW ZEALAND": [
    -44.355829501126,
    171.245639505714
  ],
  "Mill Farm, 140 Mill Road, Pleasant Point, NEW ZEALAND": [
    -44.265509897035,
    171.175810699899
  ],
  "Morrinsville Road, Hamilton, 3286, NEW ZEALAND": [
    -37.796178386917,
    175.333092140655
  ],
  "P O Box 58 263, Botany, Manukau, 2163, NEW ZEALAND": [
    -36.99282,
    174.87986
  ],
  "Papatoetoe, Auckland, NEW ZEALAND": [
    -36.9682,
    174.84019
  ],
  "Po Box 132142, Sylvia Park, Auckland, 1644, NEW ZEALAND": [
    -36.9146569,
    174.8415617
  ],
  "Po Box 230262, Botany, Auckland, 2163, NEW ZEALAND": [
    -36.909269093796,
    174.917569274269
  ],
  "Po Box 58396, Botany, Auckland, 2163, NEW ZEALAND": [
    -36.909269093796,
    174.917569274269
  ],
  "Queen Street, Masterton, NEW ZEALAND": [
    -40.952109189326,
    175.658019986115
  ],
  "Ramrock Rd, R D 1, Waikouaiti, NEW ZEALAND": [
    -45.600010037965,
    170.645335363071
  ],
  "Spirax Sarco Ltd, Po Box 64-12, Botany, Auckland, 2163, NEW ZEALAND": [
    -36.899800122203,
    174.918793400246
  ],
  "Sugar Lane, Frankton, Queenstown, NEW ZEALAND": [
    -45.018178441567,
    168.715938534041
  ],
  "Suite 19 Suncourt Centre, 19 Tamamutu St, Taupo, 0000, NEW ZEALAND": [
    -38.686354965291,
    176.071712866459
  ],
  "Suite 3, 277 Te Irirangi Drive, Flat Bush, Auckland, 2019, NEW ZEALAND": [
    -36.96507352263,
    174.901999251406
  ],
  "Suite 5, 277 Te Irirangi Drive, Flat Bush, Auckland, 2019, NEW ZEALAND": [
    -36.96507352263,
    174.901999251406
  ],
  "Syron Farms, Main Road, Waimangaroa, NEW ZEALAND": [
    -41.71488816,
    171.764674361
  ],
  "Third Floor Como House, 51 Tancred Street, Hokitika, NEW ZEALAND": [
    -42.716925373635,
    170.962998453045
  ],
  "Unit 1, 5 Scott Road, Hobsonville, Auckland, 0616, NEW ZEALAND": [
    -36.801846435667,
    174.657656967015
  ],
  "Unit 1/2 Windsor Road, Northmead, New South Wales, 2152, AUSTRALIA": [
    -33.793042681084,
    150.998323322739
  ],
  "Unit 11, 2 Progressive Way, East Tamaki, Auckland, 2019, NEW ZEALAND": [
    -36.961611754709,
    174.896922667928
  ],
  "Unit 13, 18 Airborne Road, Albany, NEW ZEALAND": [
    -36.743577163081,
    174.700734836376
  ],
  "Unit 16a, 9 Laidlaw Way, East Tamaki, Auckland, 2019, NEW ZEALAND": [
    -36.96081694074,
    174.896618404843
  ],
  "Unit 2, 6 Keith Hay Drive, Manukau City, NEW ZEALAND": [
    -36.998851214563,
    174.867209313187
  ],
  "Unit 7, 13 Laidlaw Way, East Tamaki, Auckland, 2019, NEW ZEALAND": [
    -36.960605549142,
    174.896713287987
  ],
  "Vickerman Street, Nelson, NEW ZEALAND": [
    -41.260445967128,
    173.279868612148
  ]
}